gridfs_fuse/__init__.py
gridfs_fuse/main.py
gridfs_fuse/operations.py
gridfs_fuse/pymongo_compat.py
gridfs_fuse-0.1.2.dev1.dist-info/DESCRIPTION.rst
gridfs_fuse-0.1.2.dev1.dist-info/METADATA
gridfs_fuse-0.1.2.dev1.dist-info/RECORD
gridfs_fuse-0.1.2.dev1.dist-info/WHEEL
gridfs_fuse-0.1.2.dev1.dist-info/entry_points.txt
gridfs_fuse-0.1.2.dev1.dist-info/metadata.json
gridfs_fuse-0.1.2.dev1.dist-info/top_level.txt
