Metadata-Version: 2.0
Name: gridfs-fuse
Version: 0.1.2.dev1
Summary: A FUSE wrapper around MongoDB gridfs using python and llfuse.
Home-page: https://github.com/axiros/py_gridfs_fuse
Author: UNKNOWN
Author-email: UNKNOWN
License: BSD License
Platform: UNKNOWN
Requires-Dist: llfuse
Requires-Dist: pymongo
